{
    "data": [
      {
        "context": "Consignor/Shipper: VIET HOA TRANSPORT SERVICE AND TRADING CO., LTD 284 NGUYEN TAT THANH STR, WARD 13, DIST 4, HCMC, VIETNAM TEL: 848 39402520 FAX: 848 39411087  Forwarders Ref.  Customs Reference/Status  Page: 1  Shippers Reference Bill of Lading No. HCMBKK030112022  Consigned to Order of: SUGATTI FREIGHT INT'L (THAILAND) CO., LTD 11/38 SUKHUMVIT ROAD FRAXANONG, KLONGTOEY TEL: 662 - 7123395 FAX: 662 712 3394  Notify party: SAME AS ABOVE  PENANSHIN SHIPPING HCM CO.,LTD Country: Vietnam Port: HOCHIMINH Tel: +84 2871079090 Fax: +84 2871069090 Email: general@penanshin.com.vn Addr: ROOM 6.32 , 6 FLOOR , TOWER B, RIVERGATE BUILDING NO 151-155 BEN VAN DON STR, WARD 6, DISTRICT 4, HCM CITY, VIETNAM  Booking Reference BKK03011 Place of Reciept HOCHIMINH CFS Vessel HANSA OSTERBURG V.040S  Placeof ofLoading Loading Port HOCHIMINH,CFS VIETNAM  Port of Discharge BANGKOK CFS  BILL OF LADING  Place of Delivery BANGKOK CFS  Contents, weight, value and measurement according to senders declaration  Marks & Number  Number and Kind of Packages, Description of Goods  Gross Weight  CBM/ Volume  LCL/LCL  PART OF DRY CONTAINER STC 29 CTNS S.T.C WAVEN FABRIC PATTERN NO. MD39 100 PCT POLY ESTER WIDTH: 58'' PO NO. TTI0903/00054. TTI0903/00066  1,899.58 kgs  6.000 CBM  SHIPPING MARKS: THONG THAI TEXTILE CO., LTD BANGKOK THAILAND. COLOR : C/NO : 1 - 9, 1 - 20 COUNTRY OF ORIGIN : VIETNAM  FREIGHT PREPAID CONTAINER & SEAL NO: CSLU2082865/21567932 Total: TWENTY NINE (29) CARTONS ONLY (Original B/L Surrendered In HOCHIMINH CITY)  According to declaration of the consignor. The goods and instructions are accepted and dealt with suject to the Company's Standard Conditions Taken in charge in apparent good order and condition, unless otherwise noted herein, at the place of reciept for transport and delivery as mentioned above. Freight Payable At DESTINATION  Freight Amount Cargo Insurance through the undersigned Not covered: Yes/ No Covered according to attached policy: Yes/ No  No. of Original B/Lading ZERO  For delivery of goods please apply to: PENANSHIN SHIPPING (THAILAND) LTD. 731/32 RATCHADAPISEK ROAD, BANGPONGPENG YANNAWA, BANGKOK 10120, THAILAND TEL: (662) 6839199, FAX: (662) 6839177-78  Place and Date of Issue HO CHI MINH 01 DEC, 2022",
        "qas": [
          {
            "id": "1",
            "question": "Who is the shipper?",
            "answers": [
              {
                "text": "VIET HOA TRANSPORT SERVICE AND TRADING CO., LTD 284 NGUYEN TAT THANH STR, WARD 13, DIST 4, HCMC, VIETNAM",
                "answer_start": 19
              }
            ],
            "is_impossible": false
          },
          {
            "id": "2",
            "question": "Who is the consignee?",
            "answers": [
              {
                "text": "SUGATTI FREIGHT INT'L (THAILAND) CO., LTD 11/38 SUKHUMVIT ROAD FRAXANONG, KLONGTOEY",
                "answer_start": 291
              }
            ],
            "is_impossible": false
          },
          {
            "id": "3",
            "question": "Who is the notify party?",
            "answers": [
              {
                "text": "SAME AS ABOVE",
                "answer_start": 427
              }
            ],
            "is_impossible": false
          },
          {
            "id": "4",
            "question": "What is the port of loading?",
            "answers": [
              {
                "text": "HOCHIMINH,CFS VIETNAM",
                "answer_start": 821
              }
            ],
            "is_impossible": false
          },
          {
            "id": "5",
            "question": "What is the port of discharge?",
            "answers": [
              {
                "text": "BANGKOK CFS",
                "answer_start": 862
              }
            ],
            "is_impossible": false
          },
          {
            "id": "6",
            "question": "What is the place of delivery?",
            "answers": [
              {
                "text": "BANGKOK CFS",
                "answer_start": 909
              }
            ],
            "is_impossible": false
          },
          {
            "id": "7",
            "question": "What is the bill of lading number?",
            "answers": [
              {
                "text": "HCMBKK030112022",
                "answer_start": 251
              }
            ],
            "is_impossible": false
          },
          {
            "id": "8",
            "question": "What is the place and date of issue?",
            "answers": [
              {
                "text": "HO CHI MINH 01 DEC, 2022",
                "answer_start": 2221
              }
            ],
            "is_impossible": false
          },
          {
            "id": "9",
            "question": "How many packages are there?",
            "answers": [
              {
                "text": "29",
                "answer_start": 1125
              }
            ],
            "is_impossible": false
          },
          {
            "id": "10",
            "question": "What kind of package is it?",
            "answers": [
              {
                "text": "CTNS",
                "answer_start": 1128
              }
            ],
            "is_impossible": false
          },
          {
            "id": "11",
            "question": "What is the gross weight?",
            "answers": [
              {
                "text": "1,899.58",
                "answer_start": 1237
              }
            ],
            "is_impossible": false
          },
          {
            "id": "12",
            "question": "What is the gross weight unit?",
            "answers": [
              {
                "text": "kgs",
                "answer_start": 1246
              }
            ],
            "is_impossible": false
          },
          {
            "id": "13",
            "question": "What is the description of goods?",
            "answers": [
              {
                "text": "WAVEN FABRIC PATTERN NO. MD39 100 PCT POLY ESTER WIDTH: 58'' PO NO. TTI0903/00054. TTI0903/00066",
                "answer_start": 1139
              }
            ],
            "is_impossible": false
          },
          {
            "id": "14",
            "question": "What is the dimension or tonnage?",
            "answers": [
              {
                "text": "6.000 CBM",
                "answer_start": 1251
              }
            ],
            "is_impossible": false
          },
          {
            "id": "15",
            "question": "What is the container number?",
            "answers": [
              {
                "text": "CSLU2082865",
                "answer_start": 1419
              }
            ],
            "is_impossible": false
          },
          {
            "id": "16",
            "question": "What is the seal number?",
            "answers": [
              {
                "text": "21567932",
                "answer_start": 1431
              }
            ],
            "is_impossible": false
          }
        ]
      }
    ]
  }